pyagentic/__init__.py
pyagentic/logging.py
pyagentic/updates.py
pyagentic/_base/__init__.py
pyagentic/_base/_agent.py
pyagentic/_base/_context.py
pyagentic/_base/_exceptions.py
pyagentic/_base/_metaclasses.py
pyagentic/_base/_params.py
pyagentic/_base/_resolver.py
pyagentic/_base/_tool.py
pyagentic/_base/_validation.py
pyagentic/_utils/_typing.py
pyagentic/_utils/_warnings.py
pyagentic/llm/__init__.py
pyagentic/llm/_anthropic.py
pyagentic/llm/_mock.py
pyagentic/llm/_openai.py
pyagentic/llm/_provider.py
pyagentic/models/llm.py
pyagentic/models/response.py
pyagentic/models/tracing.py
pyagentic/tracing/__init__.py
pyagentic/tracing/_basic.py
pyagentic/tracing/_langfuse.py
pyagentic/tracing/_tracer.py
pyagentic_core-1.7.0.dist-info/licenses/LICENSE
pyagentic_core-1.7.0.dist-info/METADATA
pyagentic_core-1.7.0.dist-info/WHEEL
pyagentic_core-1.7.0.dist-info/top_level.txt
pyagentic_core-1.7.0.dist-info/RECORD
