Metadata-Version: 2.4
Name: pyagentic-core
Version: 1.7.0
Summary: Build LLM Agents in a Pythonic way
Author-email: Ryan Mikulec <rmikulec.dev@gmail.com>
License: MIT
Classifier: Programming Language :: Python :: 3
Classifier: License :: OSI Approved :: MIT License
Classifier: Operating System :: OS Independent
Requires-Python: >=3.13
License-File: LICENSE
Requires-Dist: colorlog>=6.9.0
Requires-Dist: dotenv>=0.9.9
Requires-Dist: ipykernel>=6.29.5
Requires-Dist: taskipy>=1.14.1
Requires-Dist: openai>=1.99.3
Requires-Dist: pydantic>=2.11.7
Requires-Dist: typeguard>=4.4.4
Requires-Dist: c3linearize>=0.1.0
Requires-Dist: anthropic>=0.62.0
Dynamic: license-file
